MANIFEST.in
README
setup.py
django_green_comments.egg-info/PKG-INFO
django_green_comments.egg-info/SOURCES.txt
django_green_comments.egg-info/dependency_links.txt
django_green_comments.egg-info/top_level.txt
green_comments/.models.py.swp
green_comments/__init__.py
green_comments/admin.py
green_comments/forms.py
green_comments/models.py
green_comments/settings.py
green_comments/urls.py
green_comments/views.py
green_comments/templates/green_comments/_comment_details.html
green_comments/templates/green_comments/_comment_form.html
green_comments/templates/green_comments/comment_create.html
green_comments/templates/green_comments/comment_tree.html
green_comments/templatetags/__init__.py
green_comments/templatetags/green_comments_tags.py