Metadata-Version: 1.0
Name: django-green-comments
Version: 0.1.8
Summary: Threaded comments application
Home-page: http://bitbucket.org/lorien/django-green-comments/
Author: Grigoriy Petukhov
Author-email: lorien@lorien.name
License: BSD
Keywords: django application comments threaded
Platform: UNKNOWN
Classifier: Development Status :: 4 - Beta
Classifier: Environment :: Web Environment
Classifier: Framework :: Django
Classifier: Intended Audience :: Developers
Classifier: License :: OSI Approved :: BSD License
Classifier: Operating System :: OS Independent
Classifier: Programming Language :: Python
Classifier: Topic :: Software Development :: Libraries :: Python Modules
